package/hatch_build.py
package/setup.py
package/src/s2n-py/__init__.py
s2n/__init__.py
s2n/s2nscanner/__init__.py
s2n/s2nscanner/__main__.py
s2n/s2nscanner/finding.py
s2n/s2nscanner/interfaces.py
s2n/s2nscanner/main.py
s2n/s2nscanner/report.py
s2n/s2nscanner/scan_engine.py
s2n/s2nscanner/auth/dvwa_adapter.py
s2n/s2nscanner/cli/__init__.py
s2n/s2nscanner/cli/config_builder.py
s2n/s2nscanner/cli/mapper.py
s2n/s2nscanner/cli/runner.py
s2n/s2nscanner/cli/test_runner.py
s2n/s2nscanner/crawler/__init__.py
s2n/s2nscanner/http/client.py
s2n/s2nscanner/plugins/__init__.py
s2n/s2nscanner/plugins/brute_force/__init__.py
s2n/s2nscanner/plugins/brute_force/brute_force_cache.py
s2n/s2nscanner/plugins/brute_force/brute_force_config.py
s2n/s2nscanner/plugins/brute_force/brute_force_crawling.py
s2n/s2nscanner/plugins/brute_force/brute_force_dvwa_helper.py
s2n/s2nscanner/plugins/brute_force/brute_force_main.py
s2n/s2nscanner/plugins/brute_force/brute_force_selenium.py
s2n/s2nscanner/plugins/csrf/__init__.py
s2n/s2nscanner/plugins/csrf/csrf_constants.py
s2n/s2nscanner/plugins/csrf/csrf_main.py
s2n/s2nscanner/plugins/csrf/csrf_scan.py
s2n/s2nscanner/plugins/csrf/csrf_utils.py
s2n/s2nscanner/plugins/file_upload/__init__.py
s2n/s2nscanner/plugins/file_upload/file_upload_main.py
s2n/s2nscanner/plugins/file_upload/file_upload_utils.py
s2n/s2nscanner/plugins/file_upload/test_file_upload_main.py
s2n/s2nscanner/plugins/oscommand/__init__.py
s2n/s2nscanner/plugins/oscommand/oscommand_main.py
s2n/s2nscanner/plugins/oscommand/oscommand_utils.py
s2n/s2nscanner/plugins/sqlinjection/__init__.py
s2n/s2nscanner/plugins/sqlinjection/sqli_config.py
s2n/s2nscanner/plugins/sqlinjection/sqli_dvwa_helper.py
s2n/s2nscanner/plugins/sqlinjection/sqli_main.py
s2n/s2nscanner/plugins/xss/__init__.py
s2n/s2nscanner/plugins/xss/conftest.py
s2n/s2nscanner/plugins/xss/xss.py
s2n/s2nscanner/plugins/xss/xss_scanner.py
test/conftest.py
test/test_csrf_data.py
test/test_csrf_main.py
test/test_csrf_scan.py
s2n-0.2.1.dist-info/METADATA
s2n-0.2.1.dist-info/WHEEL
s2n-0.2.1.dist-info/entry_points.txt
s2n-0.2.1.dist-info/top_level.txt
s2n-0.2.1.dist-info/RECORD
