Metadata-Version: 2.4
Name: s2n
Version: 0.2.1
Summary: Plugin-based web vulnerabillity scanner library
Author-email: 503+1 <imapversion4@gmail.com>
Project-URL: Homepage, https://github.com/504s2n/s2n
Project-URL: Repository, https://github.com/504s2n/s2n
Project-URL: Issues, https://github.com/504s2n/s2n/issues
Requires-Python: >=3.9
Requires-Dist: requests>=2.28.0
Requires-Dist: beautifulsoup4>=4.12
Requires-Dist: selenium>=4.20
Requires-Dist: webdriver-manager
Requires-Dist: click>=8.0
Requires-Dist: rich>=13.0
Provides-Extra: dev
Requires-Dist: pytest; extra == "dev"
Requires-Dist: build; extra == "dev"
Requires-Dist: twine; extra == "dev"
